ToolsPydantic/__init__.py
ToolsPydantic/abstract_py_tools.py
ToolsPydantic/file_reader_py_tools.py
ToolsPydantic/read_private_network_py_tools.py
ToolsPydantic/list_project_files_py_tools/__init__.py
ToolsPydantic/list_project_files_py_tools/constants.py
ToolsPydantic/list_project_files_py_tools/list_project_files_py_tools.py
tools_pydantic-0.2.0.dist-info/METADATA
tools_pydantic-0.2.0.dist-info/WHEEL
tools_pydantic-0.2.0.dist-info/licenses/LICENSE
tools_pydantic-0.2.0.dist-info/RECORD
