Metadata-Version: 2.4
Name: tools-pydantic
Version: 0.2.0
Summary: Pydantic-powered tools for building reliable, type-safe AI agents.
Project-URL: Homepage, https://github.com/mseyfayi/py-tools
Project-URL: Issues, https://github.com/mseyfayi/py-tools/issues
Author-email: Mohammad Seyfayi <mohammad.seyfayi@tapsi.cab>
License: MIT
License-File: LICENSE
Requires-Python: >=3.13
Requires-Dist: hatchling>=1.27.0
Requires-Dist: pydantic-ai>=0.7.2
Requires-Dist: pytest-cov>=6.2.1
Requires-Dist: pytest>=8.4.1
Requires-Dist: setuptools>=61.0
